passgen/__init__.py
passgen/cli.py
passgen/passgen.py
passgen_mk-1.0.0.dist-info/LICENSE
passgen_mk-1.0.0.dist-info/METADATA
passgen_mk-1.0.0.dist-info/WHEEL
passgen_mk-1.0.0.dist-info/entry_points.txt
passgen_mk-1.0.0.dist-info/top_level.txt
passgen_mk-1.0.0.dist-info/RECORD
