Metadata-Version: 2.1
Name: passgen-mk
Version: 1.0.0
Summary: Generates a password consisting of selected characters and the specified length.
Home-page: https://gitlab.com/marekkon/passgen
Author: Marek Konopka
Author-email: git@marek-konopka.com
License: ICS
Keywords: console password-generator
Platform: UNKNOWN
Classifier: Development Status :: 5 - Production/Stable
Classifier: License :: OSI Approved :: ISC License (ISCL)
Classifier: Environment :: Console
Classifier: Programming Language :: Python :: 3 :: Only
Classifier: Programming Language :: Python :: 3.6
Classifier: Programming Language :: Python :: 3.7
Classifier: Programming Language :: Python :: 3.8
Classifier: Topic :: Security :: Cryptography
Classifier: Intended Audience :: Developers
Provides-Extra: dev
Requires-Dist: pytest ; extra == 'dev'
Requires-Dist: flake8 ; extra == 'dev'
